{
  "tickets": [
    {
      "id": 1,
      "client": "Some Task Title 1",
      "location": "Yada Yada",
      "assigned_to": {
        "id": 101,
        "first_name": "Bob",
        "last_name": "Vila"
      },
      "date": "2023-04-19",
      "description": "blah blah blah blah blah",
      "work_completed": "this is some work completed text..."
    },
    {
      "id": 2,
      "client": "Another Title 2",
      "location": "Yada Yada",
      "assigned_to": {
        "id": 102,
        "first_name": "Corey",
        "last_name": "Trevorson"
      },
      "date": "2023-04-19",
      "description": "blah blah blah blah blah",
      "work_completed": "this is some work completed text..."
    },
    {
      "id": 3,
      "client": "Task Number 3",
      "location": "Yada Yada",
      "assigned_to": {
        "id": 102,
        "first_name": "Corey",
        "last_name": "Trevorson"
      },
      "date": "2023-04-19",
      "description": "blah blah blah blah blah UPDATED !!!!!!\nddddd\nasdf\nasdddddddddd\naaaaa\n\nAdd some \"quotes\" into this. What will happen?",
      "work_completed": "blah blah blah blah blah UPDATED !!!!!!\nddddd\nasdf\n\nasdfasdf\n\nasdf\nasdddddddddd\naaaaa"
    },
    {
      "id": 4,
      "client": "This is Task 4",
      "location": "Yada Yada",
      "assigned_to": {
        "id": 102,
        "first_name": "Corey",
        "last_name": "Trevorson"
      },
      "date": "2023-04-19",
      "description": "blah blah blah blah blah\n\nthis is updated",
      "work_completed": "this is some work completed text...\n\nand some more."
    },
    {
      "id": 5,
      "client": "Yet Another Task 5",
      "location": "Yada Yada",
      "assigned_to": {
        "id": 102,
        "first_name": "Corey",
        "last_name": "Trevorson"
      },
      "date": "2023-04-18",
      "description": "This is some test job description detail stuff...\n\nIt will probably come in list from, or multiple lines.\n- Just\n- Like\n- This",
      "work_completed": "this is some work completed text..."
    }
  ]
}